app/__init__.py
app/greet.py
vuln_repo-0.0.4.dist-info/METADATA
vuln_repo-0.0.4.dist-info/WHEEL
vuln_repo-0.0.4.dist-info/top_level.txt
vuln_repo-0.0.4.dist-info/RECORD
