Metadata-Version: 2.1
Name: vuln-repo
Version: 0.0.4
Summary: vulnerable repo
Home-page: UNKNOWN
Author: v1per
Author-email: test@test.com
License: UNKNOWN
Keywords: vulnerable,test
Platform: UNKNOWN
Classifier: Development Status :: 1 - Planning
Classifier: Intended Audience :: Developers
Classifier: Programming Language :: Python :: 3
Classifier: Operating System :: Unix
Classifier: Operating System :: MacOS :: MacOS X
Classifier: Operating System :: Microsoft :: Windows
Requires-Dist: insecure-package (==0.1.0)
Requires-Dist: flask (==0.6.1)
Requires-Dist: django (<=4.0.1)
